{
  "code": 0,
  "message": "Success",
  "zpData": {
    "pageType": 0,
    "selfAccess": false,
    "securityId": "8ukeLMuaR4RrT-D1Mlpa-rEUBGgHG_ycKmhzku5QOz2LgwTgTMVQMIe-uVihPvf1ZSL_AQVxkgJUO5kPa-sou0DgEjc0aNN2ZM1_m7KASCkad8FAnZo7jvAkycEQHQBtEwI5kvBHwaKmMkjn3JIc",
    "sessionId": null,
    "lid": "",
    "jobInfo": {
      "encryptId": "85988cb00e2c18fb1HN-3di0GVtW",
      "encryptUserId": "3b6b8281f08467d81H1829u_ElQ~",
      "invalidStatus": false,
      "jobName": "初级JAVA",
      "position": 100101,
      "positionName": "Java",
      "location": 101010100,
      "locationName": "北京",
      "experienceName": "1-3年",
      "degreeName": "本科",
      "jobType": 0,
      "proxyJob": 0,
      "proxyType": 0,
      "salaryDesc": "9-10K",
      "payTypeDesc": null,
      "postDescription": "1、有一年及以上的项目开发经验，熟练使用常用开发工具、中间件，\n2、能够独立完成开发任务，有良好的沟通能力，熟悉金融行业相关业务。\n3、熟悉Spring Boot、Spring MVC、mybatis、mq（kafka、rebitmq）、redis等开源框架；",
      "encryptAddressId": "b1984e8a19d68397031839-0ElE~",
      "address": "北京丰台区丰科中心111",
      "longitude": 116.30408,
      "latitude": 39.829215,
      "staticMapUrl": "https://img.bosszhipin.com/beijin/amap/staticMap/11615ef53f97fc878f3243b9e537b6e7",
      "pcStaticMapUrl": "https://img.bosszhipin.com/beijin/amap/staticMap/d52d109789860951c1fba13140648c28",
      "overseasAddressList": [],
      "overseasInfo": null,
      "showSkills": [
        "Java",
        "Hibernate",
        "MySQL",
        "MyBatis",
        "Spring",
        "Oracle"
      ],
      "anonymous": 0,
      "jobStatusDesc": "招聘中"
    },
    "bossInfo": {
      "name": "王先生",
      "title": "招聘主管",
      "tiny": "https://img.bosszhipin.com/beijin/upload/avatar/20240802/607f1f3d68754fd048004a36330415d3aadba2090f79e733b65c7946ca3ed629fea63fa9d5bf969_b.jpg",
      "large": null,
      "activeTimeDesc": "刚刚活跃",
      "bossOnline": true,
      "brandName": "上海艾融软件",
      "bossSource": 0,
      "certificated": true,
      "tagIconUrl": null,
      "avatarStickerUrl": null
    },
    "brandComInfo": {
      "encryptBrandId": "e6852b38bafe6b911XB93920",
      "brandName": "上海艾融软件",
      "logo": "https://img.bosszhipin.com/beijin/mcs/banner/6ec612c89cc8e2e93363d04176fc783bcfcd208495d565ef66e7dff9f98764da.jpg",
      "stage": 807,
      "stageName": "已上市",
      "scale": 305,
      "scaleName": "1000-9999人",
      "industry": 100021,
      "industryName": "计算机软件",
      "introduce": "艾融软件股份有限公司（简称：艾融软件）股票代码830799，艾融（互联.智能.金融），是致力于互联网与金融业务整合的上市公司，专注研究新一代电子银行业务模式及产品创新，推动互联网金融智能化。在上海，北京，广州设立分支机构，其核心团队，拥有网上银行领域众多的成功咨询、产品及实施经验。         艾融创造了互联网银行的客户体验六边形模型，以科学的理论和实践为依据，围绕互联网金融业务的功能、安全、服务、用户界面、技术、成本这六个关键领域，为电子银行业务提供高端咨询和快速、前瞻、可量化、支持多渠道管理的电子银行产品及解决方案。更进一步将艾融互联网创新理念和技术应用到金融行业客户，为其提供更多功能、更加安全、更便利的互联网金融交易软件产品。         艾融科技核心团队的服务过客户有国内知名国有、股份制、及城市商业银行，包括：中国工商银行、中国建设银行、中国农业银行、中国银行、交通银行、中信银行、华夏银行、北京银行、上海银行、宁波银行等。并与国内知名企业金山软件、普元软件、北京数字认证中心、IBM、ORACLE、ChinaUI、北京理工大学软件测试中心、浙江理工大学可用性实验室等建立紧密战略合作关系。艾融科技秉承为客户提供超值产品及服务为宗旨，为中国银行客户提供网上银行业务咨询、实施和服务，持续地为客户创造价值。",
      "labels": [
        "五险一金",
        "定期体检",
        "加班补助",
        "带薪年假",
        "零食下午茶",
        "团建聚餐",
        "节日福利",
        "生日福利"
      ],
      "activeTime": 1729595661355,
      "visibleBrandInfo": true,
      "focusBrand": false,
      "customerBrandName": "上海艾融软件",
      "customerBrandStageName": "已上市"
    },
    "oneKeyResumeInfo": {
      "inviteType": 0,
      "alreadySend": false,
      "canSendResume": false,
      "canSendPhone": false,
      "canSendWechat": false
    },
    "relationInfo": {
      "interestJob": false,
      "beFriend": false
    },
    "handicappedInfo": null,
    "appendixInfo": {
      "canFeedback": false,
      "chatBubble": null
    },
    "atsOnlineApplyInfo": {
      "inviteType": 0,
      "alreadyApply": false
    }
  }
}