{
  "code": 0,
  "message": "Success",
  "zpData": {
    "pageType": 0,
    "selfAccess": false,
    "securityId": "bGZX9aQq3GT29-O1zsFdP3yaf8XrmjBROHgX95iqZoP52UfdZnRuiLn4ujfvxGq2BR2kwO5Q4Fp0BvKjBUG5SvqxND9gxBYd-XipE2hj1L5mFQwH9Doc",
    "sessionId": null,
    "lid": "",
    "jobInfo": {
      "encryptId": "c925a52e12e3a2221HBy3Ny4EVtZ",
      "encryptUserId": "be18709be27d331c0nd92dS-FlNU",
      "invalidStatus": false,
      "jobName": "Testbed工程师",
      "position": 100301,
      "positionName": "测试工程师",
      "location": 101200100,
      "locationName": "武汉",
      "experienceName": "经验不限",
      "degreeName": "本科",
      "jobType": 0,
      "proxyJob": 0,
      "proxyType": 0,
      "salaryDesc": "6-8K",
      "payTypeDesc": null,
      "postDescription": "C/C++代码测试，动态测试，静态测试，熟练使用Testbed测试工具",
      "encryptAddressId": "b51d726fb90c29f31HF_3928FQ~~",
      "address": "武汉江夏区七一九所藏龙岛科研综合大楼杨桥湖大道19号",
      "longitude": 114.432498,
      "latitude": 30.427319,
      "staticMapUrl": "https://img.bosszhipin.com/beijin/amap/staticMap/06fdf81f502ea31d492e9b28d57bf2b5",
      "pcStaticMapUrl": "https://img.bosszhipin.com/beijin/amap/staticMap/a4982c77b47ffee17c584d7c18964bc0",
      "overseasAddressList": [],
      "overseasInfo": null,
      "showSkills": [
        "C++"
      ],
      "anonymous": 0,
      "jobStatusDesc": "招聘中"
    },
    "bossInfo": {
      "name": "洪先生",
      "title": "高级工程师",
      "tiny": "https://img.bosszhipin.com/beijin/boss/avatar/hSg_mbK7.jpg",
      "large": null,
      "activeTimeDesc": "刚刚活跃",
      "bossOnline": false,
      "brandName": "中国船舶重工集团...",
      "bossSource": 0,
      "certificated": true,
      "tagIconUrl": null,
      "avatarStickerUrl": null
    },
    "brandComInfo": {
      "encryptBrandId": "ccef2b35d7bed93f1nR439S5FVM~",
      "brandName": "中国船舶重工集团...",
      "logo": null,
      "stage": 0,
      "stageName": "",
      "scale": 305,
      "scaleName": "1000-9999人",
      "industry": 101405,
      "industryName": "半导体/芯片",
      "introduce": "中国船舶重工集团公司第七一九研究所是我国唯一的核动力舰船总体设计研究所，是集总体研究、设计、民用产业化等业务的多学科、多专业的国家重点科研院所，办公地点位于武汉市。\n获得“全国文明单位”、“全国先进基层党组织”和“全国五一劳动奖状”等荣誉，获得国家级科技进步特等奖3项，省部级以上奖项300余项，先后多人获得“感动中国人物”、“全国先进工作者”、“全国五一劳动奖章”、“中国青年五四奖章”等荣誉。设有1个博士后工作站，2个博士点，2个硕士点。\n现拥有以中国核潜艇之父、2013年度感动中国人物、中国工程院黄旭华院士及国家重点战略装备工程总师、中国工程院张金麟院士为代表的国家级、省部级专家60余人，型号总师8人，船舶设计大师3人，享受国务院特殊津贴专家28人。\n主要军品任务涵盖核动力舰船总体研究设计、系统技术抓总及研究设计、全寿期技术服务、特种设备研制、大型专项试验、防险救生及技术保障等重大职责使命。主要民品业务包括：海洋核动力平台、核电设施、石油测井、节能环保等工程研制、船舶与海洋工程研究设计及信息系统集成等。\n所区环境幽美，人文氛围浓厚，科研条件和办公环境优越，是你实现理想抱负，成就事业、报效祖国的明智选择。",
      "labels": [
        "五险一金",
        "定期体检",
        "全勤奖",
        "年终奖",
        "带薪年假",
        "员工旅游",
        "餐补",
        "交通补助",
        "包吃",
        "节日福利",
        "住房补贴"
      ],
      "activeTime": 1727502084500,
      "visibleBrandInfo": true,
      "focusBrand": false,
      "customerBrandName": "中国船舶重工集团...",
      "customerBrandStageName": ""
    },
    "oneKeyResumeInfo": {
      "inviteType": 0,
      "alreadySend": false,
      "canSendResume": false,
      "canSendPhone": false,
      "canSendWechat": false
    },
    "relationInfo": {
      "interestJob": false,
      "beFriend": false
    },
    "handicappedInfo": null,
    "appendixInfo": {
      "canFeedback": false
    },
    "atsOnlineApplyInfo": {
      "inviteType": 0,
      "alreadyApply": false
    }
  }
}