{
  "code": 0,
  "message": "Success",
  "zpData": {
    "pageType": 0,
    "selfAccess": false,
    "securityId": "tERuqqP92A58K-s1H0jpF0BXWuuer3wlS8wUpUuwDY8n_l1OCKjInuOl1RrrBn_jz61gzIUJWtxZ1SsuLBNO_L_-xQ2aMgnZTnpOWs02iJpFg4wu5BIP1MvJgLw8fpBKCGa0EiQKyA~~",
    "sessionId": null,
    "lid": "",
    "jobInfo": {
      "encryptId": "ba8867cdabf186571nN42928E1ZX",
      "encryptUserId": "f5faa9891c3fb7e41nd42d29FFo~",
      "invalidStatus": false,
      "jobName": "桌面运维",
      "position": 100401,
      "positionName": "运维工程师",
      "location": 101210100,
      "locationName": "杭州",
      "experienceName": "经验不限",
      "degreeName": "大专",
      "jobType": 0,
      "proxyJob": 0,
      "proxyType": 0,
      "salaryDesc": "4-7K·13薪",
      "payTypeDesc": null,
      "postDescription": "岗位职责：\n1、具备良好的沟通表达能力 \n2、电脑打印机安装及熟悉简单的问题处理 \n2、熟悉TCP/IP协议原理，熟悉数通网络的基本操作配置，可以单独处理基本的网络问题及线路故障问题",
      "encryptAddressId": "fcdce3a7051145341nR539u9Fg~~",
      "address": "杭州西湖区紫金广场C座1007",
      "longitude": 120.0957,
      "latitude": 30.307787,
      "staticMapUrl": "https://img.bosszhipin.com/beijin/amap/staticMap/4ec4b75464f4cfae95c093ac034c889e",
      "pcStaticMapUrl": "https://img.bosszhipin.com/beijin/amap/staticMap/998a20abea4442bdb663fdd0ff6fe2c2",
      "overseasAddressList": [],
      "overseasInfo": null,
      "showSkills": [
        "桌面运维"
      ],
      "anonymous": 0,
      "jobStatusDesc": "招聘中"
    },
    "bossInfo": {
      "name": "陈女士",
      "title": "招聘者",
      "tiny": "https://img.bosszhipin.com/beijin/boss/avatar/hSg_mbK5.jpg",
      "large": null,
      "activeTimeDesc": "半年前活跃",
      "bossOnline": false,
      "brandName": "杭州信宜德",
      "bossSource": 0,
      "certificated": true,
      "tagIconUrl": null,
      "avatarStickerUrl": null
    },
    "brandComInfo": {
      "encryptBrandId": "622fbd79e54562791HN-0ty8",
      "brandName": "杭州信宜德",
      "logo": "https://img.bosszhipin.com/beijin/upload/com/workfeel/20210526/146f90f02257d774a6914fd89fe92e3a98e31581530fb42f6de6cafd64103b29.jpg",
      "stage": 801,
      "stageName": "未融资",
      "scale": 302,
      "scaleName": "20-99人",
      "industry": 100021,
      "industryName": "计算机软件",
      "introduce": "杭州信宜德信息技术有限公司成立于2013年，公司注册资金8000万元，是专业从事网络信息系统建设、信息安全集成、高性能计算、数据中心建设等的高科技企业。\n多年来，我们致力于发展高端信息技术服务和体系建设，为客户提供整体服务，不断加快自我发展，整合厂商资源，建构起一条集售前咨询规划、系统实施建设和运维体系建设为一体的完善的服务价值链，为用户量身定制全面、专业、响应快捷的行业解决方案。",
      "labels": [
        "五险一金",
        "定期体检",
        "加班补助",
        "全勤奖",
        "年终奖",
        "带薪年假",
        "员工旅游",
        "餐补",
        "通讯补贴",
        "交通补助",
        "节日福利",
        "住房补贴"
      ],
      "activeTime": 1717121743460,
      "visibleBrandInfo": true,
      "focusBrand": false,
      "customerBrandName": "杭州信宜德",
      "customerBrandStageName": "未融资"
    },
    "oneKeyResumeInfo": {
      "inviteType": 0,
      "alreadySend": false,
      "canSendResume": false,
      "canSendPhone": false,
      "canSendWechat": false
    },
    "relationInfo": {
      "interestJob": false,
      "beFriend": false
    },
    "handicappedInfo": null,
    "appendixInfo": {
      "canFeedback": false
    },
    "atsOnlineApplyInfo": {
      "inviteType": 0,
      "alreadyApply": false
    }
  }
}