{
  "code": 0,
  "message": "Success",
  "zpData": {
    "pageType": 0,
    "selfAccess": false,
    "securityId": "Rk0V1iypRAl7r-k1EtZEyBRKXct34we9dFVMXO2nEV2ytPxZmP_GCUJL5hYfOOV7ozeVrgJTVOlSijW7txBtZS0aKeWxfOUEtffw_9TK8VM8Eu4bVzJWRofCkOxrrsIikoce6YXa9x9A",
    "sessionId": null,
    "lid": "",
    "jobInfo": {
      "encryptId": "6fbc84fde93fb6461HB929y5FlBQ",
      "encryptUserId": "ecfe0bd7ac3ffae01HB73tW1FlQ~",
      "invalidStatus": false,
      "jobName": "初级软件开发工程师",
      "position": 100109,
      "positionName": "Python",
      "location": 101191100,
      "locationName": "常州",
      "experienceName": "经验不限",
      "degreeName": "本科",
      "jobType": 0,
      "proxyJob": 0,
      "proxyType": 0,
      "salaryDesc": "5-10K",
      "payTypeDesc": null,
      "postDescription": "岗位职责：\n1、负责移动机器人系统软件的开发\n2、负责权限产品的ROS驱动开发\n3、负责机器人相关算法研究与测试\n4、进行功能仿真和实际测试\n\n任职要求：\n1、计算机相关专业/数学/机器人/人工智能等，本科及以上学历；经验不限\n2、有计算机编程基础，熟悉C++/python；英语六级；\n3、了解ROS系统，了解机器人导航原理，有相关机器人项目经验优先；\n4、熟悉linux系统，熟悉shell脚本，熟悉git，cmake等相关工具优先；\n5、具有良好的程序设计能力与动手能力，参加过机器人相关比赛优先；\n6、有较强的协调沟通能力，较好的团队合作精神，学习能力强，有责任感。",
      "encryptAddressId": "42a3971af53e87fa0XB62Nq4FVc~",
      "address": "常州武进区常州天安数码城C座1001",
      "longitude": 119.956637,
      "latitude": 31.668595,
      "staticMapUrl": "https://img.bosszhipin.com/beijin/amap/staticMap/5ad3d393811efadcb683f5901a146a69",
      "pcStaticMapUrl": "https://img.bosszhipin.com/beijin/amap/staticMap/dcca9ae84b87798bb2a696645ca3feed",
      "overseasAddressList": [],
      "overseasInfo": null,
      "showSkills": [
        "Python",
        "C++",
        "Linux开发/部署经验"
      ],
      "anonymous": 0,
      "jobStatusDesc": "招聘中"
    },
    "bossInfo": {
      "name": "舒先生",
      "title": "研发总监",
      "tiny": "https://img.bosszhipin.com/beijin/boss/avatar/hSg_mbK7.jpg",
      "large": null,
      "activeTimeDesc": "本月活跃",
      "bossOnline": false,
      "brandName": "江苏贝叶斯机器人...",
      "bossSource": 0,
      "certificated": true,
      "tagIconUrl": null,
      "avatarStickerUrl": null
    },
    "brandComInfo": {
      "encryptBrandId": "1f94db30a6ac8df81nF529u7GVI~",
      "brandName": "江苏贝叶斯机器人...",
      "logo": "https://c-res.zhipin.com/jrs/2ab84090dbe6f77ce05e46af19e109ae.jpg",
      "stage": 803,
      "stageName": "A轮",
      "scale": 302,
      "scaleName": "20-99人",
      "industry": 100018,
      "industryName": "智能硬件",
      "introduce": "江苏贝叶斯机器人有限公司成立于2019年，是一家以L4无人驾驶技术为核心的高新技术企业。\n       贝叶斯机器人（ AIBAYES ）在导航、算法、云端、软/硬件、驱动、控制方面开展研究，积累了机器人动力总成系统技术。并以此为载体与垂直场景深度结合，已广泛应用在市政大厅、医院、CBD、科技园区、高校园区等，成为专业的无人驾驶全场景解决方案提供商。\n       公司创始人兼CEO董超，英国南安普顿大学硕士，百强人工智能企业创始团队成员，具有12年服务机器人项目管理经验，主导参与多项医疗服务机器人产品研发工作。公司核心团队成员曾就职于华为、中兴、中国电子科技集团、科沃斯、Finisar等知名高科技企业，累积行业经验超过30年。\n        公司是第十一批“龙城英才计划”项目，荣获恰佩克2019年“新锐企业奖”，是英特尔&硬蛋机器人创新生态合作伙伴。公司累计申请专利100多项，其中发明专利占比30%，获得ISO 9001、14001、20001、27001、45001体系认证，CR机器人产品认证等。   \n      公司开发的BUDDY智能服务机器人，已陆续应用在常州大数据产业园、南京英特尔未来科技智慧园区、苏州市科学技术协会、海军特色医学中心等。",
      "labels": [
        "五险一金",
        "年终奖",
        "带薪年假",
        "零食下午茶",
        "绩效奖金"
      ],
      "activeTime": 1718876704000,
      "visibleBrandInfo": true,
      "focusBrand": false,
      "customerBrandName": "江苏贝叶斯机器人...",
      "customerBrandStageName": "A轮"
    },
    "oneKeyResumeInfo": {
      "inviteType": 0,
      "alreadySend": false,
      "canSendResume": false,
      "canSendPhone": false,
      "canSendWechat": false
    },
    "relationInfo": {
      "interestJob": false,
      "beFriend": false
    },
    "handicappedInfo": null,
    "appendixInfo": {
      "canFeedback": false
    },
    "atsOnlineApplyInfo": {
      "inviteType": 0,
      "alreadyApply": false
    }
  }
}