{
  "code": 0,
  "message": "Success",
  "zpData": {
    "pageType": 0,
    "selfAccess": false,
    "securityId": "21ZaiGnKeSrFH-W11azazJfBjL2wGRFIPBcZ8jwHtzyYGgwQmDEepyrkvIGK8uf3GFmXlyry-hmdKbeYbD32gb01MFy7I7ZNKY839Nd_lrOsA8T3HT28NhFrMuVlxoYxuS3h2xmjpO55zXSzrVxGUTw8",
    "sessionId": null,
    "lid": "",
    "jobInfo": {
      "encryptId": "af3c31cc366b7f7b1HF90928E1JQ",
      "encryptUserId": "154a2aaa802a949b0XZ50ty6E1ZV",
      "invalidStatus": false,
      "jobName": "自动化技术员",
      "position": 100803,
      "positionName": "自动化",
      "location": 101281600,
      "locationName": "东莞",
      "experienceName": "1-3年",
      "degreeName": "中专/中技",
      "jobType": 0,
      "proxyJob": 0,
      "proxyType": 0,
      "salaryDesc": "8-11K",
      "payTypeDesc": null,
      "postDescription": "任职要求：\n1、三年以上大型非标机台组立及调试经验；\n2、熟悉非标自动化设备装配组立调试；\n3、熟悉常规装配工艺和测试工艺，懂气缸，导轨，传感器等元器件的装配调试；\n4、熟悉光电开关，接近开关，电磁阀，气缸，变频器，电机，编码器等电控料件；\n5、能看懂Solidwork机械图纸和CAD图纸，装配图，了解治具的设计及加工等。",
      "encryptAddressId": "94d8536f58e943af03B62Nq0GFBTxIy8U_o~",
      "address": "东莞怡昌电子信息产业项目厚街怡昌电子信息产业园",
      "longitude": 113.686588,
      "latitude": 22.910356,
      "staticMapUrl": "https://img.bosszhipin.com/beijin/upload/amap_proxy/20230626/48ba41acc9cef1bfeedbc266476fe867eccbc133278b15946bb61e3b7bce0931da574d19d1d82c88.jpg.webp",
      "pcStaticMapUrl": "https://img.bosszhipin.com/beijin/upload/amap_proxy/20230626/48ba41acc9cef1bff5b978cae5c612cd7e1d94918f8a47c96bb61e3b7bce0931da574d19d1d82c88.jpg.webp",
      "overseasAddressList": [],
      "overseasInfo": null,
      "showSkills": [
        "SolidWorks"
      ],
      "anonymous": 0,
      "jobStatusDesc": "招聘中"
    },
    "bossInfo": {
      "name": "姚女士",
      "title": "招聘",
      "tiny": "https://img.bosszhipin.com/beijin/boss/avatar/hSg_mbK0.jpg",
      "large": null,
      "activeTimeDesc": "刚刚活跃",
      "bossOnline": true,
      "brandName": "环力智能科技有限公司",
      "bossSource": 0,
      "certificated": true,
      "tagIconUrl": null,
      "avatarStickerUrl": null
    },
    "brandComInfo": {
      "encryptBrandId": "57bb4ef3120572051nZ53N-8F1I~",
      "brandName": "环力智能科技有限公司",
      "logo": "https://img.bosszhipin.com/beijin/mcs/chatphoto/20210129/831eff6ec2ffdf729c1c0bcb73b353dc168cd4957a2cf6ff480cb65c2bb48d6a_s.jpg",
      "stage": 801,
      "stageName": "未融资",
      "scale": 305,
      "scaleName": "1000-9999人",
      "industry": 100903,
      "industryName": "原材料及加工/模具",
      "introduce": "东莞市环力智能科技有限公司创立于2007年,是一家集研发、生产、销售于一体的综合性现代化高新科技企业。公司主要从事智能设备、机器人配件设计及精密电子产品的开发及制造。产品范围包括精密塑胶制品、精密五金制品、精密电子产品、MIM精密零件、复合板材等电子智能高科技产品。\n     公司为华为、小米、OPPO、联想、摩托罗拉、华硕、三星、魅族、中兴、TCL、金立、天陇、传音、努比亚、奇酷、BQ、中国电信、中国移动、微软、诺基亚、亚马逊、海信、小辣椒、锤子、乐视、酷派等一线客户提供创新技术支持与产品解决方案，拥有多项科研成果，处于业界领先水平。\n公司总部位于东莞长安镇咸西社区景泰街11号。厂区主要分布在咸西社区、厦岗、寮步、虎门怀德、上角等地。厂房占地超21000平方米，职工超过2200人。",
      "labels": [
        "五险一金",
        "加班补助",
        "全勤奖",
        "员工旅游",
        "包吃",
        "节日福利",
        "住房补贴"
      ],
      "activeTime": 1724054847711,
      "visibleBrandInfo": true,
      "focusBrand": false,
      "customerBrandName": "环力智能科技有限公司",
      "customerBrandStageName": "未融资"
    },
    "oneKeyResumeInfo": {
      "inviteType": 0,
      "alreadySend": false,
      "canSendResume": false,
      "canSendPhone": false,
      "canSendWechat": false
    },
    "relationInfo": {
      "interestJob": false,
      "beFriend": false
    },
    "handicappedInfo": null,
    "appendixInfo": {
      "canFeedback": false
    },
    "atsOnlineApplyInfo": {
      "inviteType": 0,
      "alreadyApply": false
    }
  }
}