{
  "code": 0,
  "message": "Success",
  "zpData": {
    "pageType": 0,
    "selfAccess": false,
    "securityId": "HEZ579LS5Dw0k-j1R7Nk5zPyi5D13bVEyTgiF_KDjAK_pSixIjWh-kykE8yaY7PK6gQg0KXi5OLnKb1Js5RDhBn2FfG-mNGb7Coyj1DuMj3iNd03wiMo",
    "sessionId": null,
    "lid": "",
    "jobInfo": {
      "encryptId": "479cc3add2280a211HJ829y_FltU",
      "encryptUserId": "420c6406320868bd1nZ63N67F1JV",
      "invalidStatus": false,
      "jobName": "软件测试",
      "position": 100309,
      "positionName": "软件测试",
      "location": 101280600,
      "locationName": "深圳",
      "experienceName": "经验不限",
      "degreeName": "大专",
      "jobType": 0,
      "proxyJob": 0,
      "proxyType": 0,
      "salaryDesc": "4-8K",
      "payTypeDesc": null,
      "postDescription": "岗位职责：\n\n1、负责公司自主研发软件产品的测试工作，确保软件质量符合标准；\n\n2、参与测试用例的设计与执行，对发现的问题进行记录和跟踪，与开发团队紧密合作，确保问题及时被识别和解决；\n\n3、参与对外的技术支持服务，收集与反馈客户的需求、软件bug问题、意见反馈, 与技术、产品沟通，跟进落实解决；\n\n4、配合编写用户文档（安装手册、调试手册、使用手册、帮助手册等）；\n\n5、对工作进行总结，并提出切实可行的优化改进措施；\n\n6、配合领导完成其他的工作事项。\n\n\n任职要求：\n\n1、大专及以上学历，计算机软件相关专业，接受实习生（应届毕业生）；\n\n2、能够独立完成测试任务，具有较强的分析和问题解决能力；\n\n3、具有良好的团队合作精神，能够与团队成员有效沟通。",
      "encryptAddressId": "3614ff9743367aac33N43tS1EVM~",
      "address": "深圳龙岗区林展财富大厦6楼6012",
      "longitude": 114.176277,
      "latitude": 22.640034,
      "staticMapUrl": "https://img.bosszhipin.com/beijin/amap/staticMap/c1f87a4497bf0e4e12cc2d6ff05cc7db",
      "pcStaticMapUrl": "https://img.bosszhipin.com/beijin/amap/staticMap/7d90e388be303f74ae028c52c3cb5afc",
      "overseasAddressList": [],
      "overseasInfo": null,
      "showSkills": [
        "测试工作经验",
        "功能测试",
        "计算机相关专业",
        "软件开发经验"
      ],
      "anonymous": 0,
      "jobStatusDesc": "招聘中"
    },
    "bossInfo": {
      "name": "夏女士",
      "title": "客服经理",
      "tiny": "https://img.bosszhipin.com/beijin/boss/avatar/hSg_mbK8.jpg",
      "large": null,
      "activeTimeDesc": "3日内活跃",
      "bossOnline": false,
      "brandName": "肯欣科技",
      "bossSource": 0,
      "certificated": true,
      "tagIconUrl": null,
      "avatarStickerUrl": null
    },
    "brandComInfo": {
      "encryptBrandId": "e91b407df7328f671nRy09m6E1I~",
      "brandName": "肯欣科技",
      "logo": "https://img.bosszhipin.com/beijin/icon/894ce6fa7e58d64d57e7f22d2f3a9d18afa7fcceaa24b8ea28f56f1bb14732c0.png",
      "stage": 801,
      "stageName": "未融资",
      "scale": 302,
      "scaleName": "20-99人",
      "industry": 100021,
      "industryName": "计算机软件",
      "introduce": "",
      "labels": [],
      "activeTime": 1725436670520,
      "visibleBrandInfo": true,
      "focusBrand": false,
      "customerBrandName": "肯欣科技",
      "customerBrandStageName": "未融资"
    },
    "oneKeyResumeInfo": {
      "inviteType": 0,
      "alreadySend": false,
      "canSendResume": false,
      "canSendPhone": false,
      "canSendWechat": false
    },
    "relationInfo": {
      "interestJob": false,
      "beFriend": false
    },
    "handicappedInfo": null,
    "appendixInfo": {
      "canFeedback": false
    },
    "atsOnlineApplyInfo": {
      "inviteType": 0,
      "alreadyApply": false
    }
  }
}