{
  "code": 0,
  "message": "Success",
  "zpData": {
    "pageType": 0,
    "selfAccess": false,
    "securityId": "IZRWX4aBZFuOU-r1BiJtV4sBAYJ47r7xkE9G8gJvIw_29vhdGBQNIhOqofV9d1Iuaq_tg2VO346zq_L7aXPI-Xb4hO6L7RNWXrU9nYPsrnLMirXOUA~~",
    "sessionId": null,
    "lid": "",
    "jobInfo": {
      "encryptId": "d254964166f57e161n1429y1FlFT",
      "encryptUserId": "94940755486437d40XN53Nm_GFU~",
      "invalidStatus": false,
      "jobName": "测试工程师",
      "position": 100301,
      "positionName": "测试工程师",
      "location": 101180100,
      "locationName": "郑州",
      "experienceName": "1-3年",
      "degreeName": "大专",
      "jobType": 0,
      "proxyJob": 0,
      "proxyType": 0,
      "salaryDesc": "6-8K",
      "payTypeDesc": null,
      "postDescription": "岗位职责：\n1、 针对客户需求编制测试方案，参加测试方案的讨论、整改工作，负责跟客户沟通测试内容；\n2、 制定测试计划，安排测试内容；按计划进行测试实施；\n3、 负责本专业测试验证的组织与实施，指导测试助理的工作； 熟悉数据中心相关专业的设计、验收规范；\n4、负责数据中心相关主要设备（UPS、柴油发电机组、冷水机组、精密空调、安防、动环等）测试验收；对测试过程产生的数据整理、归档填表，针对存在的问题提出合理化整改建议；\n5、 汇总数据编制测试验收报告，提交成果。\n\n任职要求：\n1、 专科及以上学历，电气及其自动化、空调制冷或建筑环境类、给排水、暖通工程等专业；\n2、 具有电气、制冷、智能化的基础知识，持有特殊工种操作证或上岗证；\n3、 工作认真负责、有独立判断力、有主动学习意识和团队精神；\n4、 良好的表达、沟通能力，具有团队合作精神；",
      "encryptAddressId": "87a18dd86128351f1XZ_09S_GVo~",
      "address": "郑州管城回族区青青美庐8号楼8号楼7栋",
      "longitude": 113.740496,
      "latitude": 34.715702,
      "staticMapUrl": "https://img.bosszhipin.com/beijin/amap/staticMap/cc2f046d70cff4efa2189d2ac3fddb86",
      "pcStaticMapUrl": "https://img.bosszhipin.com/beijin/amap/staticMap/e0d3c4bcff13e96229ea2dcfac0ed8b0",
      "overseasAddressList": [],
      "overseasInfo": null,
      "showSkills": [
        "硬件测试",
        "负载测试",
        "自动化测试",
        "性能测试",
        "功能测试",
        "系统测试"
      ],
      "anonymous": 0,
      "jobStatusDesc": "招聘中"
    },
    "bossInfo": {
      "name": "胡女士",
      "title": "HR",
      "tiny": "https://img.bosszhipin.com/beijin/upload/avatar/20220511/607f1f3d68754fd0e7d5d302871abc1fdfa1945f71d14582832c9959c96a862fe9c9c5890ff_b.jpg",
      "large": null,
      "activeTimeDesc": "半年前活跃",
      "bossOnline": false,
      "brandName": "中能测",
      "bossSource": 0,
      "certificated": true,
      "tagIconUrl": null,
      "avatarStickerUrl": null
    },
    "brandComInfo": {
      "encryptBrandId": "14dd9c9ea39c2d441HB52d26GQ~~",
      "brandName": "中能测",
      "logo": "https://img.bosszhipin.com/beijin/mcs/chatphoto/20190214/db68abf74942bafb8925e74e89cac09e1c4caeb9e1e82a4ff5df9526b934ec60.png",
      "stage": 801,
      "stageName": "未融资",
      "scale": 302,
      "scaleName": "20-99人",
      "industry": 100005,
      "industryName": "大数据",
      "introduce": "中能测（北京）科技发展有限公司初创团队来源于1955 年成立的北方电信科研所，经过多年发展，先后合并了一家具有多年检测经验和设备生产制造的科技类公司，并收购一家专业ISP通讯运行类公司。\n经过多年的持续投入和研发，2006年改制成股份公司，2016 年融资重组，现拥有独立知识产权的智能化测试仪器上百种及专利技术二十余项，并与中国计量研究院、上海电科所、中国数据中心产业发展联盟、中国信息协会等建立长期的合作关系，在服务于通信，金融，电力，医疗，石油，航天，交通，教育，军工等二十多个行业。\n作为专业的第三方测试服务公司，把运维操作从被动响应式管理提高到主动预判式管理，降低运维过程中人为因素产生的事故隐患。同时，通过智能化的管理办法，消减设备运维管理中的专业人员队伍建设成本。依托通信电力检测标准，通过对通信用供电设备检测维护的经验，建立完善的电力测试维护计划，制定了完善的电力设备验收及维护的解决方案。\n       公司在依托长期伙合作伴提供的验收维护大型供电设备机会同时，自2001年成功开发研制出智能交流负载测试系统，填补了我国大功率交流电源检测领域的多项空白。并通过不断的研发升级，使公司这个系列的产品性能可以与美国FLUKE公司产品测量精度媲美。\n       公司在现有的JZC技术模块的基础之上，建立了一套完整的开发体系，使公司的设备更具有可移植性，可以根据用户的要求定制不同功率的产品，通过建立开放的技术协议，更能接近以及满足多行业多专业广泛的需求，不仅扩大了客户群，而且使公司每个新产品占到20%到30%比例的技术创新。\n       通过建立云测试及云运维平台，建立机电设施全生命周期可追溯性，为以后国内预测式检测技术及对机电设施分析及改进建立大数据支撑，通过智能化的云服务系统，以数字化、模块化、系统化的构建方式，帮助客户量身定做精准的设备“健康档案”，做到设备问题可预判、故障问题可及时预警、设备历史问题可追溯、解决方案可存储、设备正常运行中的反馈式关怀。",
      "labels": [
        "五险一金",
        "补充医疗保险",
        "带薪年假",
        "交通补助",
        "节日福利"
      ],
      "activeTime": 1722914169315,
      "visibleBrandInfo": true,
      "focusBrand": false,
      "customerBrandName": "中能测",
      "customerBrandStageName": "未融资"
    },
    "oneKeyResumeInfo": {
      "inviteType": 0,
      "alreadySend": false,
      "canSendResume": false,
      "canSendPhone": false,
      "canSendWechat": false
    },
    "relationInfo": {
      "interestJob": false,
      "beFriend": false
    },
    "handicappedInfo": null,
    "appendixInfo": {
      "canFeedback": false
    },
    "atsOnlineApplyInfo": {
      "inviteType": 0,
      "alreadyApply": false
    }
  }
}