{
  "code": 0,
  "message": "Success",
  "zpData": {
    "pageType": 0,
    "selfAccess": false,
    "securityId": "xNa28hTyJ9Tz8-k1phoKC30-LZSzfGavEwJ5DHnKoPmiVsXoNI3-ENkg75IEwjcFEoi8vj7RGWVISdlWu_PPqqkoafoI42SoBfrI0o6UlZocX0WvjS2Tcmw4HuQENQHh4bhXJd6cC-Q3Z0A~",
    "sessionId": null,
    "lid": "",
    "jobInfo": {
      "encryptId": "25ec4e9e3de63f471Hx82t-_ElNW",
      "encryptUserId": "8baa45af4df989650nd52dW4EVBU",
      "invalidStatus": false,
      "jobName": "Python数据开发（六险一金+双休）",
      "position": 100508,
      "positionName": "数据开发",
      "location": 101250100,
      "locationName": "长沙",
      "experienceName": "1-3年",
      "degreeName": "本科",
      "jobType": 0,
      "proxyJob": 0,
      "proxyType": 0,
      "salaryDesc": "7-10K·13薪",
      "payTypeDesc": null,
      "postDescription": "欢迎您来加入一个鼓励创新、拥抱挑战、充满动力的团队，公司目前以全球各类内容网站的开发运营为主，类型丰富多样，如儿童版块有益智问答、游戏等，有信息咨询整合网站等，至今已在全球拥有超十亿用户。\n\n1、努力就会有回报：\n（1）综合薪资7-10k。薪资结构=底薪+绩效+餐补\n（2）业绩奖金上不封顶\n2、专属成长规划：双晋升通道、入职导师带教、行业大咖培训\n3、梦想家园计划: 首套购房无息贷(最高30W)\n4、工作安全感拉满:\n（1）入职六险一金，全额缴纳最高比例如公积金12%\n（2）员工年度免费全面体检\n（3）父母保险&节日礼物\n5、人性化关怀：\n(1)带薪年假带薪病假、全天供应零食&饮料、好玩的员工社团：桌游社..有趣的团建：滑雪、密室等\n(2)长沙市内面试可为您全额报销面试打车费用~\n其他：\n（1）试用期：试用期时间6个月，可提前转正。试用期薪资不打折，同样缴纳社保公积金；\n（2）工作时间：早十晚七，周末双休，节假日与国家同步\n\n岗位职责：\n1. 理解公司产品需求，负责各个平台的数据包括运营、用户行为等，对收集到的数据进行清洗、整理和存储，确保数据的准确性和完整性；\n2. 基于对业务理解的基础上，对接产品与运营的数据需求，为运营提供数据支持；\n4. 对日常数据进行统计、分析和监控；\n任职要求：\n1. 本科及以上学历，统计、数学、计算机等相关专业优先；\n2. 良好的数据分析能力，有数据分析、挖掘和清洗的经验优先；\n3. 熟悉python编程语言，熟悉常用的python库如Pandas、NumPy等；\n4. 了解并运用 SQL进行数据提取；\n5. 善于沟通，具有良好的团队合作精神。",
      "encryptAddressId": "f02ffd0d8bee76bd3nBy2dq7E1o~",
      "address": "长沙岳麓区中建智慧谷3区2栋3楼",
      "longitude": 112.944309,
      "latitude": 28.153539,
      "staticMapUrl": "https://img.bosszhipin.com/beijin/upload/amap_proxy/20230405/48ba41acc9cef1bfd8becc67d44971f86f787ef9a49974e96bb61e3b7bce0931da574d19d1d82c88.jpg",
      "pcStaticMapUrl": "https://img.bosszhipin.com/beijin/upload/amap_proxy/20230530/48ba41acc9cef1bf7edfe77603315d5f99bab129b96796126bb61e3b7bce0931da574d19d1d82c88.jpg",
      "overseasAddressList": [],
      "overseasInfo": null,
      "showSkills": [
        "大数据开发经验",
        "计算机相关专业",
        "Python",
        "SQL",
        "数学/统计相关专业"
      ],
      "anonymous": 0,
      "jobStatusDesc": "招聘中"
    },
    "bossInfo": {
      "name": "张女士",
      "title": "HR专家",
      "tiny": "https://img.bosszhipin.com/beijin/upload/avatar/20230602/607f1f3d68754fd02968dec62a9f0034729d10fab03765884be8582f1cc93e5047dc9442b44_b.jpg",
      "large": null,
      "activeTimeDesc": "刚刚活跃",
      "bossOnline": false,
      "brandName": "长沙探月科技有限公司",
      "bossSource": 0,
      "certificated": true,
      "tagIconUrl": null,
      "avatarStickerUrl": null
    },
    "brandComInfo": {
      "encryptBrandId": "46231e181e38dcfd1Xd80tq6FVU~",
      "brandName": "长沙探月科技有限公司",
      "logo": "https://img.bosszhipin.com/beijin/upload/com/workfeel/20240806/7bf6f160950405e99a2ab6d4d9ea9521901ca93f439fcaeca1a91eaf6dedf6f10110bb98d99bd64c.png.webp",
      "stage": 808,
      "stageName": "不需要融资",
      "scale": 303,
      "scaleName": "100-499人",
      "industry": 100020,
      "industryName": "互联网",
      "introduce": "探月简介\n长沙探月科技有限公司（简称探月科技）孵化于互联网头部企业，由资深行业从业者创办，专注于海外市场内容的开发设计与运营。公司在全球激烈的竞争中建立了核心技术壁垒, 并一直处于高速发展。\n\n用户深耕\n探月科技的产品深受全球儿童的喜爱，用户已经突破10亿, 覆盖十几个国家，包括美国，日本，法国，德国，巴西等。\n\n探月文化\n探月科技遵循“硅谷文化”和“黑客精神”, 致力于打造开心高效的工作氛围。尽管公司正处于高速发展阶段，但是开心工作是我们一直追求的目标。我们有扁平化管理，定期体检, 首付无息贷，父母养老金计划，夜宵补助等贴心的福利。因为我们相信为员工提供更愉悦的工作氛围，我们才能为用户打造有幸福感的产品。这里没有职级，没有职场文化，没有勾心斗角。一切讲究用数据说话，高效的工作效率才是我们的宗旨。欢迎：加入我们一起做最幸福的产品，做最酷的事！",
      "labels": [
        "生日福利",
        "节日福利",
        "团建聚餐",
        "零食下午茶",
        "餐补",
        "带薪年假",
        "绩效奖金",
        "年终奖",
        "意外险",
        "补充医疗保险",
        "五险一金"
      ],
      "activeTime": 1728358315334,
      "visibleBrandInfo": true,
      "focusBrand": false,
      "customerBrandName": "长沙探月科技有限公司",
      "customerBrandStageName": "不需要融资"
    },
    "oneKeyResumeInfo": {
      "inviteType": 0,
      "alreadySend": false,
      "canSendResume": false,
      "canSendPhone": false,
      "canSendWechat": false
    },
    "relationInfo": {
      "interestJob": false,
      "beFriend": false
    },
    "handicappedInfo": null,
    "appendixInfo": {
      "canFeedback": false
    },
    "atsOnlineApplyInfo": {
      "inviteType": 0,
      "alreadyApply": false
    }
  }
}