{
  "code": 0,
  "message": "Success",
  "zpData": {
    "pageType": 0,
    "selfAccess": false,
    "securityId": "tocOul043qbd--w12gXkXmG9ZviRozN9iVSiTDMIV0sPnC3Bpeve2G1hRFHgp8IeCunUXiUshnFkxHE0WJ7gAseArS9Gp2PUjDknj50qWWO1wU5l1OQ~",
    "sessionId": null,
    "lid": "",
    "jobInfo": {
      "encryptId": "9ef2bc0d1a1cd4f41XJ-2N-1GVJW",
      "encryptUserId": "a0fca32023aa53f00nV73NS8GVZT",
      "invalidStatus": false,
      "jobName": "信息安全服务工程师",
      "position": 100407,
      "positionName": "网络安全",
      "location": 101270100,
      "locationName": "成都",
      "experienceName": "1-3年",
      "degreeName": "本科",
      "jobType": 0,
      "proxyJob": 0,
      "proxyType": 0,
      "salaryDesc": "8-10K",
      "payTypeDesc": null,
      "postDescription": "岗位职责\n1、负责安全漏洞扫描、安全配置检查、安全设备维护等基础安全服务\n2、安全技术支持，包括安全事件应急响应、漏洞修补、迎检支撑等\n3、负责项目安全产品的的安装部署、配置、测试、故障处理等运维工作；\n4、熟悉网络安全软件产品（虚拟化防火墙、虚拟WAF、虚拟IPS、态势感知等），解决安全产品使用产品过程中出现的技术问题；\n5、负责信息安全技术工作，及时跟进最新安全动向，跟踪并分析最新的安全漏洞，及时推动解决信息系统中的安全隐患；\n6、负责项目内外部的安全监控和攻击事件的应对工作，做好预防性措施并定期演练；\n7、响应安全事件，对入侵检测、日志审计等安全设备日志分析取证，协助数据恢复等工作；\n任职资格:\n1、熟悉主流的网络安全产品，对防火墙、入侵检测、入侵防御、VPN、防病毒、身份认证等安全产品软硬件知识，设计、安装、配置和故障处理，至少有两年以上国内外主流网络安全产品经验；\n2、熟悉主流的安全防护技术，对网络、系统层攻击防护有清晰认识；\n3、精通网络技术，熟悉主流防火墙、IPS、VPN、WAF、防数据泄露、入侵检测、攻防技术、漏洞扫描、入侵防御、防病毒、系统加固等安全技术；\n4、掌握各类开源的安全漏洞检测扫描、安全防范、安全渗透测试、安全审计及信息管理工具；\n5、熟悉各种木马、后门原理，具备木马的发现、分析能力及操作系统安全加固能力；\n6、熟悉window系统，常用服务，掌握linux的系统常用命令，能够熟练运用相关命令编写脚本；\n7、对云计算（IaaS/PaaS/SaaS）领域有敏锐的洞察力，云安全发展方向有深入思考；\n8、信息安全、网络安全、计算机相关专业毕业，本科及以上学历\n9、相关培训以及认证，有CISSP/CISP/CCNP等网络、系统、安全认证证书优先；\n10、高度的责任心，工作细致耐心、积极主动，抗压性强，有团队合作精神。\n11、了解OSI七层模型，会基础的网络故障排查。\n上班时间及福利：\n1、五天7.5小时工作制：9:00-17:30\n2、购买五险一金\n3、额外购买商业保险\n4、提供午餐补助\n5、发放生日礼金、节日礼品、结婚礼金、生育礼金\n6、每年一次的员工体检\n7、年度旅游、部门聚会等等丰富多彩的员工活动\n8、法定节假日之外的带薪年假\n9、提供多元化的培训与在职进修机会，鼓励员工在职学习考证，报销培训考试费用的同时发放奖金奖励！",
      "encryptAddressId": "5158c729cbfaa8490Hxz29q0FVo~",
      "address": "成都武侯区棕南甲区A区1612",
      "longitude": 104.073864,
      "latitude": 30.624144,
      "staticMapUrl": "https://img.bosszhipin.com/beijin/amap/staticMap/d4e3196eb2aac193b65e40b252351da2",
      "pcStaticMapUrl": "https://img.bosszhipin.com/beijin/amap/staticMap/a9dcc4a2eda7ee19cd7dfbfb40ae13e1",
      "overseasAddressList": [],
      "overseasInfo": null,
      "showSkills": [
        "计算机/信息安全相关专业",
        "CISSP/CISP"
      ],
      "anonymous": 0,
      "jobStatusDesc": "招聘中"
    },
    "bossInfo": {
      "name": "梁女士",
      "title": "行政人事前台",
      "tiny": "https://img.bosszhipin.com/beijin/upload/avatar/20240310/607f1f3d68754fd022c1d51f89c679315c970125cdfcfa5f91f6398a4e78f8545e441b35a571f47_b.jpg",
      "large": null,
      "activeTimeDesc": "半年前活跃",
      "bossOnline": false,
      "brandName": "奥诚科技",
      "bossSource": 0,
      "certificated": true,
      "tagIconUrl": null,
      "avatarStickerUrl": null
    },
    "brandComInfo": {
      "encryptBrandId": "52ebae29a551b1d01HNz29W4Fw~~",
      "brandName": "奥诚科技",
      "logo": "https://img.bosszhipin.com/beijin/mcs/chatphoto/20190311/811ee0fa26776ed75952cfa3d7e6e0b6d94941e49f72f397ae3aed7c28eeb585_s.jpg",
      "stage": 801,
      "stageName": "未融资",
      "scale": 302,
      "scaleName": "20-99人",
      "industry": 100016,
      "industryName": "信息安全",
      "introduce": "四川奥诚科技有限责任公司是专注于通信技术服务、应用软件开发和计算机信息系统集成的高科技企业。 \n\n    奥诚公司本着“以一流的技术、规范的管理、负责任的态度，提供最优质的服务”的企业精神，和“诚信、坚韧、精进、共享”的核心价值观，致力于通讯运营商的运营数据管理、用户数据稽核、信息安全服务，及其相关技术支持和系统解决方案等业务。 \n\n    奥诚公司依托多年来对移动通信技术的理解与实际经验积累，已拥有十余项具有自主知识产权、专利技术的软件产品 。 \n\n    奥诚公司的业务立足四川，扩展至全国多个省份及海外市场。经过多年的努力，公司与中国移动、中国电信、华为、中兴、诺基亚西门子、爱立信、阿尔卡特、IBM、ORACLE、SYMANTEC、EMC、STONESOFT等通信运营商和知名厂商开展了广泛合作。",
      "labels": [
        "五险一金",
        "定期体检",
        "加班补助",
        "年终奖",
        "带薪年假",
        "员工旅游",
        "餐补",
        "节日福利"
      ],
      "activeTime": 1719467235884,
      "visibleBrandInfo": true,
      "focusBrand": false,
      "customerBrandName": "奥诚科技",
      "customerBrandStageName": "未融资"
    },
    "oneKeyResumeInfo": {
      "inviteType": 0,
      "alreadySend": false,
      "canSendResume": false,
      "canSendPhone": false,
      "canSendWechat": false
    },
    "relationInfo": {
      "interestJob": false,
      "beFriend": false
    },
    "handicappedInfo": null,
    "appendixInfo": {
      "canFeedback": false
    },
    "atsOnlineApplyInfo": {
      "inviteType": 0,
      "alreadyApply": false
    }
  }
}