{
  "code": 0,
  "message": "Success",
  "zpData": {
    "pageType": 0,
    "selfAccess": false,
    "securityId": "4xc0kaZk7Uy2t-S1iqSZGxuYZywIrRmSKrmkhsZdhsAGffPfyHkW2Ub4z6j1Xex7t4eVjybZKwr9AR9yzMSEBm-Lp3UNGgzYcc4y4F4osUqkcpumgr4m_G0XlxyztDkb6ebXWq8dhQlwLwoMxfHB-g~~",
    "sessionId": null,
    "lid": "",
    "jobInfo": {
      "encryptId": "8f068e6d93248c3b1nZy2tu4E1FQ",
      "encryptUserId": "4fee0e7136e203ce1XJ_2du5EFQ~",
      "invalidStatus": false,
      "jobName": "java开发工程师",
      "position": 100101,
      "positionName": "Java",
      "location": 101280600,
      "locationName": "深圳",
      "experienceName": "1-3年",
      "degreeName": "本科",
      "jobType": 0,
      "proxyJob": 0,
      "proxyType": 0,
      "salaryDesc": "8-13K",
      "payTypeDesc": null,
      "postDescription": "岗位职责\n1、参与相关的系统分析设计以及基础服务研发；\n2、基于架构师的框架设计，对系统总体结构框架提出一些有建设性的意见和建议，并能服从开发任务安排；\n3、能够指导初级程序员进行开发工作;\n4、能够独立完成重要关键的软件开发任务，与开发团队其他成员紧密合作；\n5、撰写相关的技术文档。\n\n任职要求\n1. 具有数学、计算机科学或相关学科本科或以上学位；\n2. 具有二年以上软件开发经验；\n3. 精通java语言和JDK中常用工具类的使用；\n4. 熟悉ssh,redis,activemq,maven等主流java开发框架；\n5. 熟悉Mysql、Oracle等至少一款主流数据库；\n6. 熟悉js、jsp技术，熟练使用Jquery框架，至少熟练一种ui框架；\n7. 工作认真，有强烈的责任心和执行力，有良好的团队合作精神。",
      "encryptAddressId": "770cacd75a741f3e1nR43tq_FlRYxom8V_yd",
      "address": "深圳南山区卓越前海壹号A座1406B",
      "longitude": 113.900504,
      "latitude": 22.529768,
      "staticMapUrl": "https://img.bosszhipin.com/beijin/upload/amap_proxy/20230407/48ba41acc9cef1bfa4d7d877a088d85dfef41ac0362bb7046bb61e3b7bce0931da574d19d1d82c88.jpg",
      "pcStaticMapUrl": "https://img.bosszhipin.com/beijin/upload/amap_proxy/20230601/48ba41acc9cef1bf4756605d4ddb00068638eff0c24c285d6bb61e3b7bce0931da574d19d1d82c88.jpg",
      "overseasAddressList": [],
      "overseasInfo": null,
      "showSkills": [
        "JDK",
        "Java",
        "Maven",
        "SpringCloud",
        "MySQL",
        "架构师",
        "微服务架构",
        "Redis",
        "SSH",
        "Spring",
        "Oracle"
      ],
      "anonymous": 0,
      "jobStatusDesc": "招聘中"
    },
    "bossInfo": {
      "name": "贾女士",
      "title": "人事主管",
      "tiny": "https://img.bosszhipin.com/beijin/upload/avatar/20240718/607f1f3d68754fd0d5bb12d7d30ea03b3ae7b6f6379326ed76f48e846751454aace3311fc9b7755_b.jpg",
      "large": null,
      "activeTimeDesc": "刚刚活跃",
      "bossOnline": true,
      "brandName": "维曼云计算",
      "bossSource": 0,
      "certificated": true,
      "tagIconUrl": null,
      "avatarStickerUrl": null
    },
    "brandComInfo": {
      "encryptBrandId": "6a3eaa894b8bb43b03J929W1Ew~~",
      "brandName": "维曼云计算",
      "logo": "https://img.bosszhipin.com/beijin/mcs/chatphoto/20190619/d5e5b9d9b4f8a10011f51c8cb12bec27e63e4fc0fd4b6389024353baf52d94b4_s.jpg",
      "stage": 801,
      "stageName": "未融资",
      "scale": 302,
      "scaleName": "20-99人",
      "industry": 100021,
      "industryName": "计算机软件",
      "introduce": "深圳市维曼云计算有限公司成立于2011年3月，办公地址位于深圳市南山区粤海街道高新园高新南七道1号粵美特大厦，主要为中小企业提供完善的云软件解决方案。公司是全球知名SaaS ERP/CRM/eCommerce服务提供商-NetSuite在大中华地区合作伙伴。目前服务的客户分布于中国大陆及中国香港地区。公司为企业客户提供基于SaaS模式的ERP/CRM/E-commerce/PSA软件平台，用专业的云产品帮助客户快速搭建具有高度扩展性和集成化的IT解决方案。我们专注于在电商、零售、分销、贸易、服务等行业为客户提供完善的一站式服务。公司拥有一支来自国外一流软件公司的精英团队，均在以上行业有极为丰富的经验，我们用一流的产品服务于快速发展的中小企业，助其腾飞，和客户建立良好的合作关系，不离不弃，以实现共同成长。基于一流的国外软件平台，公司正致力于打造自己的核心产品，助力电商零售行业腾飞。\n公司文化：开放、多元、专业、务实。\n公司官网：https://www.waymap.cn\n公司产品网站：https://www.waysuite.com",
      "labels": [
        "五险一金",
        "加班补助",
        "全勤奖",
        "年终奖",
        "带薪年假",
        "餐补",
        "节日福利",
        "零食，下午茶"
      ],
      "activeTime": 1724308401413,
      "visibleBrandInfo": true,
      "focusBrand": false,
      "customerBrandName": "维曼云计算",
      "customerBrandStageName": "未融资"
    },
    "oneKeyResumeInfo": {
      "inviteType": 0,
      "alreadySend": false,
      "canSendResume": false,
      "canSendPhone": false,
      "canSendWechat": false
    },
    "relationInfo": {
      "interestJob": false,
      "beFriend": false
    },
    "handicappedInfo": null,
    "appendixInfo": {
      "canFeedback": false
    },
    "atsOnlineApplyInfo": {
      "inviteType": 0,
      "alreadyApply": false
    }
  }
}