{
  "code": 0,
  "message": "Success",
  "zpData": {
    "pageType": 0,
    "selfAccess": false,
    "securityId": "sg94FAnjvPLgU-C1mBITcYK7xz_T_Ohtd40QFrCmAibNeHHrjnOp6mCUduvAhDXzfm3GJeqioJMXAncz0Kl8s31rwTJsq6Te_hjbUrINwmrjovOmRmkU9aENI7d2p1NMHZ67dCobFj9UJEr5IYHjKy4OoutDubMZK1Ie18CC2GEO4P9oppA~",
    "sessionId": null,
    "lid": "",
    "jobInfo": {
      "encryptId": "3d68279e57a9c9fa1Hx60t29FVRW",
      "encryptUserId": "e803b54a94a2fdc91nR53928FlpV",
      "invalidStatus": false,
      "jobName": "ACC测试",
      "position": 100301,
      "positionName": "测试工程师",
      "location": 101010100,
      "locationName": "北京",
      "experienceName": "1-3年",
      "degreeName": "大专",
      "jobType": 0,
      "proxyJob": 0,
      "proxyType": 0,
      "salaryDesc": "11-13K",
      "payTypeDesc": null,
      "postDescription": "ACC测试工程师：（1人，base北京）\n1、依据产品需求和项目要求，配合搭建并管理测试环境，对adas功能进行验证；\n2、依据测试需求设计测试用例，保证测试用例合理有效；\n3、执行测试用例，收集并跟踪测试中发现的问题，与软件开发人员共同调试与解决问题，确保问题的修复与闭环；\n4、根据研发对问题的修改结果，执行回归测试；\n5、及时发现项目的风险，并积极协助降低风险。\n任职资格：\n1、计算机类、通信、数学或其它相关专业专科及以上学历；\n2、熟悉软件测试理论和方法\n3、熟悉一般软件测试流程，熟悉常见的软件测试用例设计方法和编写方法；\n4、熟悉Linux操作系统的常见命令或操作方法；\n5、具备较好的逻辑思维、较好的沟通与表达能力，做事细致严谨，责任心强；\n6、有至少一年以上对adas产品的测试经验。",
      "encryptAddressId": "8504829327438f5f33B83Nu1E1E~",
      "address": "北京朝阳区融新科技中心C座12层",
      "longitude": 116.468895,
      "latitude": 40.021517,
      "staticMapUrl": "https://img.bosszhipin.com/beijin/amap/staticMap/442125067b554f4f6cc9e48f01fbf03e",
      "pcStaticMapUrl": "https://img.bosszhipin.com/beijin/amap/staticMap/288c9a0c752e2e460aa9cf5df39a66cf",
      "overseasAddressList": [],
      "overseasInfo": null,
      "showSkills": [
        "功能测试"
      ],
      "anonymous": 0,
      "jobStatusDesc": "最新"
    },
    "bossInfo": {
      "name": "姜女士",
      "title": "招聘",
      "tiny": "https://img.bosszhipin.com/beijin/upload/avatar/20220928/607f1f3d68754fd0b826b54da1621a105753ef169cf7fe32e8361d8757a2f023b3c774141d5_b.jpg",
      "large": null,
      "activeTimeDesc": "刚刚活跃",
      "bossOnline": true,
      "brandName": "浅雨科技",
      "bossSource": 0,
      "certificated": true,
      "tagIconUrl": null,
      "avatarStickerUrl": null
    },
    "brandComInfo": {
      "encryptBrandId": "a30f6d010ab051001XV53ti6FlA~",
      "brandName": "浅雨科技",
      "logo": "https://img.bosszhipin.com/beijin/upload/com/logo/20240226/7b5b554d84f9729ce54d1a1ecce5694d7f45624e85a46124da2f3b6831c56dea887b43b763f23cd9.jpg.webp",
      "stage": 801,
      "stageName": "未融资",
      "scale": 303,
      "scaleName": "100-499人",
      "industry": 100023,
      "industryName": "计算机服务",
      "introduce": "无锡浅雨科技有限公司成立于2022年，总部位于无锡市经开区雪浪小镇数据创新中心，是一家专业的人力资源科技公司。\n       公司以人工智能技术赋能招聘业务，从招聘流程管理、简历筛选、简历推荐、大规模面试为核心场景切入HR业务中，实现招聘全流程的数字化、智能化。\n       公司始终以产品研发为核心，用技术驱动业务为发展战略，我们致力于为IT互联网、智能制造、新能源、工业互联网等国家重点行业提供数字化、智能化的人力资源工作全生命周期服务及解决方案。浅雨利用过去十几年积累的数字化、智能化和人力资源业务服务的经验，帮助行业客户解决人力资源管理过程中的人才培养、招聘、管理等难题，提升产业服务效率，助力企业降本增效。",
      "labels": [
        "生日福利",
        "节日福利",
        "团建聚餐",
        "带薪年假",
        "定期体检",
        "补充医疗保险",
        "五险一金"
      ],
      "activeTime": 1724398817546,
      "visibleBrandInfo": true,
      "focusBrand": false,
      "customerBrandName": "浅雨科技",
      "customerBrandStageName": "未融资"
    },
    "oneKeyResumeInfo": {
      "inviteType": 0,
      "alreadySend": false,
      "canSendResume": false,
      "canSendPhone": false,
      "canSendWechat": false
    },
    "relationInfo": {
      "interestJob": false,
      "beFriend": false
    },
    "handicappedInfo": null,
    "appendixInfo": {
      "canFeedback": false
    },
    "atsOnlineApplyInfo": {
      "inviteType": 0,
      "alreadyApply": false
    }
  }
}