{
  "code": 0,
  "message": "Success",
  "zpData": {
    "pageType": 0,
    "selfAccess": false,
    "securityId": "2g5yO3TqIJxhh-51p-mqDhHQvuhY3q-X0BWxf0yUdML9tbd4dxoVFTKy-c0kiIhypvLM4Ujz8aQLe3FaSkFEHaN5QlrJwWVa9xSv4Ijc9LEmTdNNmDcn",
    "sessionId": null,
    "lid": "",
    "jobInfo": {
      "encryptId": "eaf6e354c6ad98401HF439S5EltU",
      "encryptUserId": "2ff02d8a456c3ef60nd60tS0EFFS",
      "invalidStatus": false,
      "jobName": "java开发",
      "position": 100101,
      "positionName": "Java",
      "location": 101121300,
      "locationName": "威海",
      "experienceName": "1-3年",
      "degreeName": "本科",
      "jobType": 0,
      "proxyJob": 0,
      "proxyType": 0,
      "salaryDesc": "7-12K",
      "payTypeDesc": null,
      "postDescription": "岗位职责：\n1.负责项目后端Java开发，和前端开发一起协作高质高效完成开发工作；\n2.维护优化后端Java应用；\n3.全栈开发者优先\n岗位要求：\n1、一年以上Java后端开发经验，熟悉Java8+语法；\n2、熟练掌握SpringBoot应用开发；\n3、熟练掌握Eclipse、Maven、Jenkins者优先;\n热爱新技术的学习和研究，良好的学习和沟通能力，工作积极主动、认真负责。",
      "encryptAddressId": "762d46c7dbce0ded1XV929W8",
      "address": "威海环翠区威海高技术产业开发区创新创业基地火炬路213-2号",
      "longitude": 122.04866,
      "latitude": 37.51991,
      "staticMapUrl": "https://img.bosszhipin.com/beijin/amap/staticMap/5ef0ebee95d1d6f83964789a895488a3",
      "pcStaticMapUrl": "https://img.bosszhipin.com/beijin/amap/staticMap/019fa619b1af98e49a62950b02a30a8f",
      "overseasAddressList": [],
      "overseasInfo": null,
      "showSkills": [
        "Java",
        "Spring",
        "MySQL",
        "Oracle"
      ],
      "anonymous": 0,
      "jobStatusDesc": "招聘中"
    },
    "bossInfo": {
      "name": "王女士",
      "title": "HR",
      "tiny": "https://img.bosszhipin.com/beijin/boss/avatar/hSg_mbK-.jpg",
      "large": null,
      "activeTimeDesc": "3日内活跃",
      "bossOnline": false,
      "brandName": "欣智",
      "bossSource": 0,
      "certificated": true,
      "tagIconUrl": null,
      "avatarStickerUrl": null
    },
    "brandComInfo": {
      "encryptBrandId": "f165386df1ccd04a1nJ52NS8GVo~",
      "brandName": "欣智",
      "logo": null,
      "stage": 808,
      "stageName": "不需要融资",
      "scale": 302,
      "scaleName": "20-99人",
      "industry": 100021,
      "industryName": "计算机软件",
      "introduce": "",
      "labels": [
        "补充医疗保险",
        "五险一金"
      ],
      "activeTime": 1718702816420,
      "visibleBrandInfo": true,
      "focusBrand": false,
      "customerBrandName": "欣智",
      "customerBrandStageName": "不需要融资"
    },
    "oneKeyResumeInfo": {
      "inviteType": 0,
      "alreadySend": false,
      "canSendResume": false,
      "canSendPhone": false,
      "canSendWechat": false
    },
    "relationInfo": {
      "interestJob": false,
      "beFriend": false
    },
    "handicappedInfo": null,
    "appendixInfo": {
      "canFeedback": false
    },
    "atsOnlineApplyInfo": {
      "inviteType": 0,
      "alreadyApply": false
    }
  }
}